dotz/__init__.py
dotz/cli.py
dotz/core.py
dotz/watcher.py
dotz/gui/__init__.py
dotz/gui/main.py
dotz/gui/widgets/__init__.py
dotz/gui/widgets/dashboard.py
dotz/gui/widgets/files.py
dotz/gui/widgets/init.py
dotz/gui/widgets/settings.py
dotz-0.4.0.dist-info/licenses/LICENSE
dotz-0.4.0.dist-info/METADATA
dotz-0.4.0.dist-info/WHEEL
dotz-0.4.0.dist-info/entry_points.txt
dotz-0.4.0.dist-info/top_level.txt
dotz-0.4.0.dist-info/RECORD
