Metadata-Version: 2.4
Name: dotz
Version: 0.4.0
Summary: A fully featured, Git-backed dotfiles manager for Linux
Author-email: Moustafa Salem <salemmoustafa442@gmail.com>
License-Expression: GPL-3.0-or-later
Project-URL: Homepage, https://github.com/tTrmc/dotz
Project-URL: Repository, https://github.com/tTrmc/dotz
Project-URL: Documentation, https://github.com/tTrmc/dotz#readme
Project-URL: Issues, https://github.com/tTrmc/dotz/issues
Project-URL: Changelog, https://github.com/tTrmc/dotz/releases
Keywords: dotfiles,git,configuration,linux,symlink,backup,dotz
Classifier: Development Status :: 4 - Beta
Classifier: Environment :: Console
Classifier: Intended Audience :: Developers
Classifier: Intended Audience :: End Users/Desktop
Classifier: Operating System :: POSIX :: Linux
Classifier: Programming Language :: Python :: 3
Classifier: Programming Language :: Python :: 3.9
Classifier: Programming Language :: Python :: 3.10
Classifier: Programming Language :: Python :: 3.11
Classifier: Programming Language :: Python :: 3.12
Classifier: Programming Language :: Python :: 3.13
Classifier: Topic :: System :: Archiving :: Backup
Classifier: Topic :: System :: Systems Administration
Classifier: Topic :: Utilities
Requires-Python: >=3.9
License-File: LICENSE
Requires-Dist: typer
Requires-Dist: gitpython
Requires-Dist: watchdog
Provides-Extra: gui
Requires-Dist: PySide6>=6.5.0; extra == "gui"
Provides-Extra: test
Requires-Dist: pytest>=6.0; extra == "test"
Requires-Dist: pytest-cov; extra == "test"
Provides-Extra: dev
Requires-Dist: pytest>=6.0; extra == "dev"
Requires-Dist: pytest-cov; extra == "dev"
Requires-Dist: black; extra == "dev"
Requires-Dist: isort; extra == "dev"
Requires-Dist: flake8; extra == "dev"
Requires-Dist: flake8-docstrings; extra == "dev"
Requires-Dist: flake8-bugbear; extra == "dev"
Requires-Dist: flake8-comprehensions; extra == "dev"
Requires-Dist: mypy; extra == "dev"
Requires-Dist: bandit[toml]; extra == "dev"
Requires-Dist: pydocstyle; extra == "dev"
Requires-Dist: pre-commit; extra == "dev"
Requires-Dist: build; extra == "dev"
Requires-Dist: twine; extra == "dev"
Requires-Dist: PySide6>=6.5.0; extra == "dev"
Dynamic: license-file
